tessif_examples/__init__.py
tessif_examples/basic/__init__.py
tessif_examples/basic/chp.py
tessif_examples/basic/connected_es.py
tessif_examples/basic/emission_objective.py
tessif_examples/basic/expansion_plan_example.py
tessif_examples/basic/fpwe.py
tessif_examples/basic/mwe.py
tessif_examples/basic/simple_transformer_grid_es.py
tessif_examples/basic/statistical_identification_example.py
tessif_examples/basic/storage_example.py
tessif_examples/basic/storage_fixed_ratio_expansion_example.py
tessif_examples/basic/time_varying_efficiency_transformer.py
tessif_examples/basic/zero_costs_es.py
tessif_examples/data/load_profiles/Car_Charging.csv
tessif_examples/data/load_profiles/Loads.csv
tessif_examples/data/load_profiles/Renewable_Energy.csv
tessif_examples/data/load_profiles/component_scenario_profiles.csv
tessif_examples/data/load_profiles/el_demand_HH_2019.csv
tessif_examples/data/load_profiles/solar_HH_2019.csv
tessif_examples/data/load_profiles/th_demand_HH_2019.csv
tessif_examples/data/load_profiles/wind_HH_2019.csv
tessif_examples/paths.py
tessif_examples/plausibility/__init__.py
tessif_examples/plausibility/chp_emissions.py
tessif_examples/plausibility/storage_emissions.py
tessif_examples/scientific/__init__.py
tessif_examples/scientific/component_focused.py
tessif_examples/scientific/grid_focused.py
tessif_examples/scientific/hamburg_inspired.py
tessif_examples/specialized/__init__.py
tessif_examples/specialized/generic_grid.py
tessif_examples/specialized/self_similar_system_model.py
tessif_examples/specialized/variable_chp.py
tessif_examples/utils.py
tessif_examples-0.3.2.dist-info/LICENSE
tessif_examples-0.3.2.dist-info/WHEEL
tessif_examples-0.3.2.dist-info/METADATA
tessif_examples-0.3.2.dist-info/RECORD
