Metadata-Version: 2.1
Name: tessif-examples
Version: 0.3.2
Summary: Tessif Examples Library
Home-page: https://github.com/tZ3ma/tessif_examples
License: MIT
Keywords: tessif,examples
Author: Mathias Ammon
Author-email: tz3ma.coding@use.startmail.com
Requires-Python: >=3.8,<4.0
Classifier: License :: OSI Approved :: MIT License
Classifier: Programming Language :: Python :: 3
Classifier: Programming Language :: Python :: 3.8
Classifier: Programming Language :: Python :: 3.9
Classifier: Programming Language :: Python :: 3.10
Requires-Dist: numpy
Requires-Dist: pandas
Requires-Dist: tessif (>=0.0.25)
Project-URL: Repository, https://github.com/tZ3ma/tessif_examples
